dhutil/__init__.py
dhutil/_version.py
dhutil/drive_ops.py
dhutil/drive_utils.py
dhutil/mail_ops.py
dhutil/mail_utils.py
dhutil/mailchimp_utils.py
dhutil/mongo_ops.py
dhutil/mongo_utils.py
dhutil/shared.py
dhutil/scripts/__init__.py
dhutil/scripts/dhutil_cli.py
dhutil/scripts/drive_cli.py
dhutil/scripts/mail_cli.py
dhutil/scripts/mailchimp_cli.py
dhutil/scripts/mongo_cli.py
dhutil-0.0.6.dist-info/METADATA
dhutil-0.0.6.dist-info/RECORD
dhutil-0.0.6.dist-info/WHEEL
dhutil-0.0.6.dist-info/entry_points.txt
dhutil-0.0.6.dist-info/top_level.txt
