Metadata-Version: 2.1
Name: dhutil
Version: 0.0.6
Summary: Python utilities for DataHack.
Home-page: https://github.com/DataHackIL/dhutil
Author: Shay Palachy
Author-email: shaypal5@gmail.com
License: MIT
Keywords: python datahack
Platform: any
Classifier: Development Status :: 4 - Beta
Classifier: License :: OSI Approved :: MIT License
Classifier: Programming Language :: Python
Classifier: Programming Language :: Python :: 3.5
Classifier: Programming Language :: Python :: 3.6
Classifier: Programming Language :: Python :: 3.7
Classifier: Topic :: Software Development :: Libraries
Classifier: Topic :: Software Development :: Libraries :: Python Modules
Classifier: Intended Audience :: Developers
Provides-Extra: test
Requires-Dist: pymongo
Requires-Dist: click
Requires-Dist: mailchimp3
Requires-Dist: tqdm
Requires-Dist: gspread
Requires-Dist: oauth2client
Requires-Dist: mongozen
Provides-Extra: test
Requires-Dist: pytest; extra == 'test'
Requires-Dist: coverage; extra == 'test'
Requires-Dist: pytest-cov; extra == 'test'
